hrendjango/__init__.py
hrendjango/admin.py
hrendjango/apps.py
hrendjango/constants.py
hrendjango/context_processors.py
hrendjango/converters.py
hrendjango/debug.py
hrendjango/decorators.py
hrendjango/exceptions.py
hrendjango/forms.py
hrendjango/middleware.py
hrendjango/mixins.py
hrendjango/shortcuts.py
hrendjango/template.py
hrendjango/utils.py
hrendjango/views.py
hrendjango/locale/en/LC_MESSAGES/django.mo
hrendjango/locale/en/LC_MESSAGES/django.po
hrendjango/locale/ru/LC_MESSAGES/django.mo
hrendjango/locale/ru/LC_MESSAGES/django.po
hrendjango/management/__init__.py
hrendjango/management/base.py
hrendjango/management/decorators.py
hrendjango/management/commands/__init__.py
hrendjango/management/commands/adddnshost.py
hrendjango/management/commands/createlocalizationfiles.py
hrendjango/management/commands/hrenmigrate.py
hrendjango/management/commands/installnodejs.py
hrendjango/management/commands/removednshost.py
hrendjango/management/commands/shell_translate.py
hrendjango/migrations/0001_initial.py
hrendjango/migrations/__init__.py
hrendjango/models/__init__.py
hrendjango/models/base.py
hrendjango/models/decorators.py
hrendjango/models/media.py
hrendjango/models/mixins.py
hrendjango/models/utils.py
hrendjango/static/hrendjango/css/CodeTextArea.css
hrendjango/static/hrendjango/css/hrendjango.css
hrendjango/static/hrendjango/js/CodeTextArea.js
hrendjango/static/hrendjango/js/hrendjango.js
hrendjango/templates/empty.html
hrendjango/templates/hrendjango/includes/form_context.html
hrendjango/templates/hrendjango/includes/init.html
hrendjango/templates/hrendjango/includes/init_scripts.html
hrendjango/templates/hrendjango/includes/init_styles.html
hrendjango/templates/hrendjango/widgets/ClearableFileInput.html
hrendjango/templates/hrendjango/widgets/UUIDInput.html
hrendjango/templates/hrendjango/widgets/base-input.html
hrendjango/templatetags/__init__.py
hrendjango/templatetags/hrendjango.py
hrendjango/templatetags/local_plus.py
hrendjango/templatetags/translate_text.py
hrendjango-0.1.4.dist-info/METADATA
hrendjango-0.1.4.dist-info/WHEEL
hrendjango-0.1.4.dist-info/top_level.txt
hrendjango-0.1.4.dist-info/RECORD
