Metadata-Version: 2.4
Name: hrendjango
Version: 0.1.4
Summary: Global add-on to Django
Home-page: https://github.com/MagIlyasDOMA/hrendjango
Author: Маг Ильяс DOMA (MagIlyasDOMA)
Author-email: magilyas.doma.09@list.ru
License: MIT
Classifier: Development Status :: 4 - Beta
Classifier: Intended Audience :: Developers
Classifier: Programming Language :: Python :: 3
Classifier: Programming Language :: Python :: 3.10
Classifier: Programming Language :: Python :: 3.11
Classifier: Programming Language :: Python :: 3.12
Classifier: Programming Language :: Python :: 3.13
Classifier: Programming Language :: Python :: 3.14
Classifier: Programming Language :: Python :: 3 :: Only
Requires-Python: >=3.10
Requires-Dist: django>=5.1.0
Requires-Dist: deep-translator>=1.11.4
Requires-Dist: rusgram~=0.1.0
Requires-Dist: pandas<=3.0.0,>=2.3.3
Requires-Dist: hrenpack>=2.3.0
Dynamic: author
Dynamic: author-email
Dynamic: classifier
Dynamic: home-page
Dynamic: license
Dynamic: requires-dist
Dynamic: requires-python
Dynamic: summary
